latam/__init__.py
latam/__main__.py
latam/caribe/__init__.py
latam/centro/__init__.py
latam/entidades.py
latam/example.py
latam/norte/__init__.py
latam/norte/mexico.py
latam/paises.py
latam/py.typed
latam/sur/__init__.py
latam-0.1.2.2.dist-info/entry_points.txt
latam-0.1.2.2.dist-info/LICENSE
latam-0.1.2.2.dist-info/WHEEL
latam-0.1.2.2.dist-info/METADATA
latam-0.1.2.2.dist-info/RECORD
