Metadata-Version: 2.1
Name: latam
Version: 0.1.2.2
Summary: Un paquete para trabajar facilmente con metadatos de paises en latinoamerica.
Home-page: https://github.com/tacosdedatos/latam
License: BSD-3
Author: tacosdedatos
Author-email: chekos@tacosdedatos.com
Requires-Python: >=3.7,<4.0
Classifier: Development Status :: 3 - Alpha
Classifier: Intended Audience :: Developers
Classifier: License :: Other/Proprietary License
Classifier: Operating System :: OS Independent
Classifier: Programming Language :: Python :: 3
Classifier: Programming Language :: Python :: 3.7
Classifier: Programming Language :: Python :: 3.8
Classifier: Programming Language :: Python :: 3.9
Classifier: Topic :: Software Development :: Libraries :: Python Modules
Requires-Dist: importlib_metadata (>=2.0.0,<3.0.0); python_version < "3.8"
Requires-Dist: pandas (>=1.1.3,<2.0.0)
Requires-Dist: pytz (>=2020.1,<2021.0)
Requires-Dist: rich (>=8.0.0,<9.0.0)
Requires-Dist: typer[all] (>=0.3.2,<0.4.0)
Project-URL: Repository, https://github.com/tacosdedatos/latam
